kimariplot/__init__.py
kimariplot/plotter.py
kimariplot-1.3.2.dist-info/LICENSE
kimariplot-1.3.2.dist-info/METADATA
kimariplot-1.3.2.dist-info/WHEEL
kimariplot-1.3.2.dist-info/entry_points.txt
kimariplot-1.3.2.dist-info/top_level.txt
kimariplot-1.3.2.dist-info/RECORD
