Metadata-Version: 2.1
Name: kimariplot
Version: 1.3.2
Summary: A tool for generating Kimari-plots.
Home-page: https://github.com/kimariyb/kimariPlot
Author: Kimariyb
Author-email: kimariyb@163.com
Classifier: Programming Language :: Python :: 3
Classifier: License :: OSI Approved :: MIT License
Classifier: Operating System :: OS Independent
Requires-Python: >=3.8
License-File: LICENSE
